date_operations/__init__.py
date_operations/main.py
date_operations/settings.py
date_operations-0.2.0.dist-info/LICENSE
date_operations-0.2.0.dist-info/METADATA
date_operations-0.2.0.dist-info/WHEEL
date_operations-0.2.0.dist-info/RECORD
